pypubmed/__init__.py
pypubmed/bin/__init__.py
pypubmed/bin/_citations.py
pypubmed/bin/_search.py
pypubmed/bin/cli.py
pypubmed/core/__init__.py
pypubmed/core/article.py
pypubmed/core/citations.py
pypubmed/core/eutils.py
pypubmed/core/export.py
pypubmed/util/__init__.py
pypubmed/util/pmc_xml_parser.py
pypubmed/util/pubmed_xml_parser.py
pypubmed/version/version.json
pypubmed-1.1.8.dist-info/LICENSE
pypubmed-1.1.8.dist-info/METADATA
pypubmed-1.1.8.dist-info/WHEEL
pypubmed-1.1.8.dist-info/entry_points.txt
pypubmed-1.1.8.dist-info/top_level.txt
pypubmed-1.1.8.dist-info/RECORD
