Metadata-Version: 2.1
Name: pypubmed
Version: 1.1.8
Summary: Toolkits for NCBI Pubmed
Home-page: https://github.com/suqingdong/pypubmed
Author: suqingdong
Author-email: suqingdong1114@gmail.com
License: BSD License
Project-URL: Documentation, https://pypubmed.readthedocs.io
Project-URL: Tracker, https://github.com/suqingdong/pypubmed/issues
Platform: UNKNOWN
Classifier: Development Status :: 5 - Production/Stable
Classifier: Operating System :: OS Independent
Classifier: Intended Audience :: Developers
Classifier: License :: OSI Approved :: MIT License
Classifier: Programming Language :: Python
Classifier: Programming Language :: Python :: 3
Classifier: Programming Language :: Python :: 3.6
Classifier: Topic :: Software Development :: Libraries
Requires-Dist: lxml
Requires-Dist: openpyxl
Requires-Dist: python-dateutil
Requires-Dist: w3lib
Requires-Dist: click
Requires-Dist: prettytable
Requires-Dist: webrequests
Requires-Dist: impact-factor (>=1.1.1)
Requires-Dist: simple-loggers
Requires-Dist: googletranslate-python
Requires-Dist: pmc-id-converter
